
pyfaspr
