Metadata-Version: 2.2
Name: pyfaspr
Version: 0.3.1
Summary: A python wrapper of FASPR, a fast and accurate protein sidechain builder
Home-page: https://github.com/ShintaroMinami/pyfaspr
Author: Shintaro Minami
Requires-Dist: pdbutil
Dynamic: author
Dynamic: description
Dynamic: description-content-type
Dynamic: home-page
Dynamic: requires-dist
Dynamic: summary
